porn_cli/__init__.py
porn_cli/__main__.py
porn_cli/websites/__init__.py
porn_cli/websites/porn/__init__.py
porn_cli/websites/porn/hentaimama.py
porn_cli/websites/porn/javct.py
porn_cli/websites/porn/pornhub.py
porn_cli/websites/porn/xxxmax.py
porn_cli-1.0.6.dist-info/LICENSE
porn_cli-1.0.6.dist-info/METADATA
porn_cli-1.0.6.dist-info/WHEEL
porn_cli-1.0.6.dist-info/RECORD
