Metadata-Version: 2.1
Name: porn-cli
Version: 1.0.6
Summary: An ani-cli like cli tool for porn
Home-page: https://github.com/mov-cli/porn-cli
License: GPLv3
Author: mov-cli
Author-email: mov-cli@protonmail.com
Requires-Python: >=3.9,<4.0
Classifier: License :: Other/Proprietary License
Classifier: Programming Language :: Python :: 3
Classifier: Programming Language :: Python :: 3.9
Classifier: Programming Language :: Python :: 3.10
Classifier: Programming Language :: Python :: 3.11
Requires-Dist: mov-cli (>=1.4.6,<2.0.0)
Project-URL: Bug Tracker, https://github.com/mov-cli/porn-cli/issues
Project-URL: Repository, https://github.com/mov-cli/porn-cli
